{"1": "switch.aeotec_zstick_disco_light", "2": "switch.vardagsrum_vanster_horn", "3": "switch.halldorren", "4": "switch.koksfonster_lilla", "5": "switch.switch_11", "6": "switch.switch_16", "7": "switch.sovrum_gatufonster", "8": "switch.switch_15", "9": "switch.vanster_sida_tvbank", "10": "switch.koksfonster_stora", "11": "switch.sovrum_gavelfonster", "12": "switch.moas_rum_fonster", "13": "switch.altandorr_vanster", "14": "switch.vardagsrum_hoger_horn", "15": "switch.altandorr_hoger", "16": "switch.philio_technology_corporation_unknown_type0001_id0029_switch", "17": "switch.fibaro_system_fgwpef_wall_plug_switch", "18": "switch.philio_technology_corporation_unknown_type0001_id0029_switch_2", "19": "group.all_switches", "20": "group.all_lights", "21": "switch.0b1100c6008c82aa01000050", "22": "group.kitchen_lights", "23": "group.living_room_lights", "24": "group.office_lights", "25": "group.outdoor_front_lights", "26": "group.garage_lights", "27": "group.hallway_lights", "28": "switch.switch_4", "29": "switch.hallway_masterbedroom_8", "30": "switch.masterbedoom_streetwindow_2", "31": "switch.tv_bench_left_6", "32": "switch.living_room_left_corner_3", "33": "switch.family_room_skylight_11", "34": "switch.bookshelf_left_15", "35": "switch.kitchen_streetwindow_10", "36": "switch.switch_41", "37": "switch.masterbedroom_gablewindow_1", "38": "switch.kitchen_gablewindow_12", "39": "switch.patio_door_left_9", "40": "switch.bookshelf_right_16", "41": "switch.moas_bedroom_window_14", "42": "switch.patio_door_right_5", "43": "switch.living_room_right_corner_4", "44": "switch.0b110039011e9d3e01010f30", "45": "switch.0b11013a0038202008000030", "46": "switch.0b110083011e9d3e01000040"}